{ 
  "sessions": {
    "columns": {
      "id": "INTEGER PRIMARY KEY",
      "registration_state": "TEXT",
      "last_registration_state": "TEXT",
      "access_token": "TEXT",
      "client": "TEXT",
      "uid": "TEXT",
      "user_id": "INTEGER",
      "email": "TEXT",
      "password": "TEXT",
      "consent_updated_at": "TEXT",
      "consent_last_updated_at": "TEXT",
      "consent_last_version_id": "INTEGER",
      "milestones_updated_at": "TEXT",
      "milestones_last_updated_at": "TEXT",
      "milestone_calendar_updated_at": "TEXT",
      "milestone_calendar_last_updated_at": "TEXT",
      "notifications_permission": "TEXT",
      "notification_period": "TEXT",
      "notifications_updated_at": "TEXT",
      "pending_actions": "TEXT",
      "push_token": "TEXT",
      "screening_blood": "INTEGER",
      "screening_blood_notification": "INTEGER",
      "screening_blood_physician_notification": "INTEGER",
      "screening_blood_other": "INTEGER",
      "video_presentation": "TEXT",
      "video_sharing": "TEXT",
      "current_group_index": "INTEGER",
    },
    "indexes": [],
  },
  "consents": {
    "columns": {
      "id": "INTEGER PRIMARY KEY",
      "api_id": "INTEGER",
      "study_id": "INTEGER",
      "version_id": "INTEGER",
      "irb_id": "TEXT",
      "title": "TEXT",
      "confirmation_type": "TEXT",
      "tos_approved_by": "TEXT",
      "tos_approved_on": "TEXT",
      "tos_expires_on": "TEXT",
      "created_at": "TEXT",
      "updated_at": "TEXT",
      "summary": "TEXT",
      "content": "TEXT",
    },
    "indexes": [],
  },
  "users": {
    "columns": {
      "id": "INTEGER PRIMARY KEY", 
      "api_id": "INTEGER",
      "email": "TEXT", 
      "password": "TEXT",
      "first_name": "TEXT",
      "last_name": "TEXT",
      "uid": "TEXT",
      "last_token": "TEXT",
    },
    "indexes": [],
  },
  "subjects": {
    "columns": {
      "id": "INTEGER PRIMARY KEY", 
      "api_id": "INTEGER",
      "first_name": "TEXT",
      "last_name": "TEXT",
      "middle_name": "TEXT",
      "conception_method": "TEXT",
      "gender": "TEXT",
      "expected_date_of_birth": "TEXT",
      "date_of_birth": "TEXT",
      "outcome": "TEXT",
      "date_of_loss": "TEXT",
      "days_premature": "INTEGER",
      "screening_blood": "INTEGER",
      "screening_blood_notification": "INTEGER",
      "screening_blood_other": "INTEGER",
      "video_presentation": "TEXT",
      "video_sharing": "TEXT",
    },
    "indexes": [],
  },
  "respondents": {
    "columns": {
      "id": "INTEGER PRIMARY KEY", 
      "api_id": "INTEGER",
      "user_id": "INTEGER",
      "respondent_type": "TEXT",
      "first_name": "TEXT",
      "last_name": "TEXT",
      "middle_name": "TEXT",
      "address_1": "TEXT",
      "address_2": "TEXT",
      "city": "TEXT",
      "state": "TEXT",
      "zip_code": "TEXT",
      "country_code": "TEXT",
      "email": "TEXT",
      "home_phone": "TEXT",
      "other_phone": "TEXT",
      "date_of_birth": "TEXT",
      "drivers_license_number": "TEXT",
      "marital_status": "TEXT",
      "weight": "INTEGER",
      "height": "INTEGER",
      "tos_id": "TEXT",
      "irb_id": "TEXT",
      "accepted_tos_at": "TEXT",
      "pregnant": "INTEGER",
      "push_token": "TEXT",
    },
    "indexes": [],
  },
  "respondents_subjects": {
    "columns": {
      "id": "INTEGER PRIMARY KEY", 
      "api_id": "INTEGER",
      "respondent_id": "INTEGER",
      "subject_id": "INTEGER",
    },
    "indexes": [
      "r_s_respondent_id ON respondents_subjects (respondent_id);",
      "r_s_subject_id ON respondents_subjects (subject_id);",
    ],
  },
}